pint_pal/PINT_parameters.py
pint_pal/__init__.py
pint_pal/_version.py
pint_pal/checkin.py
pint_pal/config.py
pint_pal/defaults.yaml
pint_pal/dmx_utils.py
pint_pal/ftester.py
pint_pal/lite_utils.py
pint_pal/make_release.py
pint_pal/noise_utils.py
pint_pal/notebook_runner.py
pint_pal/notebook_templater.py
pint_pal/notebook_writer.py
pint_pal/outlier_utils.py
pint_pal/par_checker.py
pint_pal/plot_settings.yaml
pint_pal/plot_utils.py
pint_pal/reflagger.py
pint_pal/report.py
pint_pal/timingconfiguration.py
pint_pal/timingnotebook.py
pint_pal/update_results.py
pint_pal/utils.py
pint_pal/write_initial_configs.py
pint_pal/yamlio.py
pint_pal-0.4.1.dist-info/LICENSE
pint_pal-0.4.1.dist-info/METADATA
pint_pal-0.4.1.dist-info/WHEEL
pint_pal-0.4.1.dist-info/top_level.txt
pint_pal-0.4.1.dist-info/RECORD
