Metadata-Version: 2.2
Name: pint_pal
Version: 0.4.1
Summary: A long-lived repository for NANOGrav Pulsar Timing analysis work.
Author-email: Joe Glaser <joe.glaser@nanograv.org>, Joe Swiggum <joe.swiggum@nanograv.org>, Thankful Cromartie <thanful.cromartie@nanograv.org>, Deborah Good <deborah.good@nanograv.org>, Anne Archibald <anne.archibald@nanograv.org>, Kevin Wilson <kevin.wilson@nanograv.org>, Ross Jennings <ross.jennings@nanograv.org>, Jeremy Baier <jeremy.baier@nanograv.org>
Project-URL: Homepage, https://github.com/nanograv/pint_pal
Project-URL: Bug Tracker, https://github.com/nanograv/pint_pal/issues
Classifier: Programming Language :: Python :: 3
Classifier: License :: OSI Approved :: MIT License
Classifier: Operating System :: OS Independent
Requires-Python: >=3.8
License-File: LICENSE
Requires-Dist: ruamel.yaml
Requires-Dist: pint_pulsar>=1.1.1
Requires-Dist: enterprise-pulsar>=3.3.2
Requires-Dist: enterprise-extensions>=v2.4.1
Requires-Dist: pytest
Requires-Dist: nbconvert
Requires-Dist: ipywidgets>=7.6.3
Requires-Dist: pypulse>=0.0.1
Requires-Dist: numpy
Requires-Dist: weasyprint
Requires-Dist: pytest-xdist[psutil]>=2.3.0
Requires-Dist: notebook
Requires-Dist: seaborn
Requires-Dist: gitpython
Requires-Dist: la-forge
Requires-Dist: arviz
Requires-Dist: fastshermanmorrison-pulsar
